{"OpenedDocuments":"[{\"DocumentPath\":\"Main.xaml\",\"FactoryId\":\"{ACB8E7BA-F093-44C1-9B50-33ECA51AAE16}\"}]","ProjectBreakpoints":"{\"Value\":{\"Framework/Process.xaml\":[{\"ConditionalExpression\":null,\"ActionExpression\":null,\"ExpectedHitCounter\":null,\"ShouldContinueAfterAction\":false,\"BreakpointType\":1,\"LocationIdentifier\":\"Log Message Process Start\",\"IsEnabled\":true,\"Annotation\":null,\"Id\":\"e92832d9-aad9-4fe8-8454-3bf81ad5ed23\",\"ActivityIdRef\":\"LogMessage_1\",\"ActivityId\":\"1.66\",\"ActivityName\":\"Log Message Process Start\",\"IsTransient\":false},{\"ConditionalExpression\":null,\"ActionExpression\":null,\"ExpectedHitCounter\":null,\"ShouldContinueAfterAction\":false,\"BreakpointType\":1,\"LocationIdentifier\":\"If\",\"IsEnabled\":true,\"Annotation\":null,\"Id\":\"8fac382b-914e-402b-bcf5-ebde4f63a713\",\"ActivityIdRef\":\"If_2\",\"ActivityId\":\"1.2\",\"ActivityName\":\"If\",\"IsTransient\":false}],\"Framework/CloseAllApplications.xaml\":[{\"ConditionalExpression\":null,\"ActionExpression\":null,\"ExpectedHitCounter\":null,\"ShouldContinueAfterAction\":false,\"BreakpointType\":1,\"LocationIdentifier\":\"Get Outlook Mail Message With UID\",\"IsEnabled\":true,\"Annotation\":null,\"Id\":\"d98ba31c-afdb-40b2-bc13-64b46e86b5e1\",\"ActivityIdRef\":\"GetMailMessageWithUID_2\",\"ActivityId\":\"1.11\",\"ActivityName\":\"Get Outlook Mail Message With UID\",\"IsTransient\":false},{\"ConditionalExpression\":null,\"ActionExpression\":null,\"ExpectedHitCounter\":null,\"ShouldContinueAfterAction\":false,\"BreakpointType\":1,\"LocationIdentifier\":\"Reply To Outlook Mail Message\",\"IsEnabled\":true,\"Annotation\":null,\"Id\":\"ca6a743f-d348-49b7-8a00-f9eee7181302\",\"ActivityIdRef\":\"ReplyToOutlookMailMessage_1\",\"ActivityId\":\"1.5\",\"ActivityName\":\"Reply To Outlook Mail Message\",\"IsTransient\":false}],\"Framework/InitAllApplications.xaml\":[{\"ConditionalExpression\":null,\"ActionExpression\":null,\"ExpectedHitCounter\":null,\"ShouldContinueAfterAction\":false,\"BreakpointType\":1,\"LocationIdentifier\":\"Assign\",\"IsEnabled\":true,\"Annotation\":null,\"Id\":\"b7d41cdc-f424-4143-98ac-39a6e5d2cab2\",\"ActivityIdRef\":\"Assign_1\",\"ActivityId\":\"1.99\",\"ActivityName\":\"Assign\",\"IsTransient\":false},{\"ConditionalExpression\":null,\"ActionExpression\":null,\"ExpectedHitCounter\":null,\"ShouldContinueAfterAction\":false,\"BreakpointType\":1,\"LocationIdentifier\":\"If\",\"IsEnabled\":true,\"Annotation\":null,\"Id\":\"fb118610-07fb-415f-b32e-4d3430682eef\",\"ActivityIdRef\":\"If_2\",\"ActivityId\":\"1.78\",\"ActivityName\":\"If\",\"IsTransient\":false},{\"ConditionalExpression\":null,\"ActionExpression\":null,\"ExpectedHitCounter\":null,\"ShouldContinueAfterAction\":false,\"BreakpointType\":1,\"LocationIdentifier\":\"Log Message\",\"IsEnabled\":false,\"Annotation\":null,\"Id\":\"9baa6efd-60d4-48c5-9656-c2049c9fa017\",\"ActivityIdRef\":\"LogMessage_7\",\"ActivityId\":\"1.6\",\"ActivityName\":\"Log Message\",\"IsTransient\":false}],\"Main.xaml\":[{\"ConditionalExpression\":null,\"ActionExpression\":null,\"ExpectedHitCounter\":null,\"ShouldContinueAfterAction\":false,\"BreakpointType\":1,\"LocationIdentifier\":\"Invoke Process workflow\",\"IsEnabled\":true,\"Annotation\":null,\"Id\":\"a4750803-d5a2-4515-aa3d-335e9369de9e\",\"ActivityIdRef\":\"InvokeWorkflowFile_24\",\"ActivityId\":\"1.210\",\"ActivityName\":\"Invoke Process workflow\",\"IsTransient\":false}]},\"CodeBreakpoints\":{}}","ProjectWatches":"{\"Value\":[]}"}